{"id":440,"date":"2015-11-05T15:04:58","date_gmt":"2015-11-05T07:04:58","guid":{"rendered":"http:\/\/demowp.cththemes.net\/outdoor\/?p=288"},"modified":"2019-09-15T03:22:24","modified_gmt":"2019-09-15T07:22:24","slug":"praesent-aliquet-tortor-2","status":"publish","type":"post","link":"https:\/\/bestpropertymarket.cththemes.com\/praesent-aliquet-tortor-2\/","title":{"rendered":"Praesent aliquet tortor"},"content":{"rendered":"<p>Lorem ipsum dosectetur adipisicing elit, sed do.Lorem ipsum dolor sit amet, consectetur Nulla fringilla purus at leo dignissim congue. Mauris elementum accumsan leo vel tempor. Sit amet cursus nisl aliquam. Aliquam et elit eu nunc rhoncus viverra quis at felis. Sed do.Lorem ipsum dolor sit amet, consectetur Nulla fringilla purus Lorem ipsum dosectetur adipisicing elit at leo dignissim congue. Mauris elementum accumsan leo vel tempor . Aliquam et elit eu nunc rhoncus viverra quis at felis. Sed do.Lorem ipsum dolor sit amet, consectetur Nulla fringilla purus Lorem ipsum dosectetur adipisicing elit at leo dignissim congue. Mauris elementum accumsan leo vel tempor<\/p>\n<blockquote><p>Vestibulum id ligula porta felis euismod semper. Sed posuere consectetur est at lobortis. Aenean eu leo quam. Pellentesque ornare sem lacinia quam venenatis vestibulum. Duis mollis, est non commodo luctus, nisi erat porttitor ligula, eget lacinia odio sem nec elit. Donec ullamcorper nulla non metus auctor fringilla. Vestibulum id ligula porta felis euismod semper.<\/p><\/blockquote>\n<p>Lorem ipsum dosectetur adipisicing elit, sed do.Lorem ipsum dolor sit amet, consectetur Nulla fringilla purus at leo dignissim congue. Mauris elementum accumsan leo vel tempor. Sit amet cursus nisl aliquam. Aliquam et elit eu nunc rhoncus viverra quis at felis. Sed do.Lorem ipsum dolor sit amet, consectetur Nulla fringilla purus Lorem ipsum dosectetur adipisicing elit at leo dignissim congue. Mauris elementum accumsan leo vel tempor . Aliquam et elit eu nunc rhoncus viverra quis at felis. Sed do.Lorem ipsum dolor sit amet, consectetur Nulla fringilla purus Lorem ipsum dosectetur adipisicing elit at leo dignissim congue. Mauris elementum accumsan leo vel tempor. Aliquam et elit eu nunc rhoncus viverra quis at felis. Sed do.Lorem ipsum dolor sit amet, consectetur Nulla fringilla purus Lorem ipsum dosectetur adipisicing elit at leo dignissim congue. Mauris elementum accumsan leo vel tempor<\/p>\n","protected":false},"excerpt":{"rendered":"<p>Ut euismod ultricies sollicitudin. Curabitur sed dapibus nulla. Nulla eget iaculis lectus. Mauris ac maximus neque. Nam in mauris quis libero sodales eleifend. Morbi varius, nulla sit amet rutrum elementum, est elit finibus tellus, ut tristique elit risus at metus.<\/p>\n<p>Lorem ipsum dolor sit amet, consectetur adipiscing elit. Maecenas in pulvinar neque. Nulla finibus lobortis pulvinar. Donec a consectetur nulla. Nulla posuere sapien vitae lectus suscipit, et pulvinar nisi tincidunt&#8230;<\/p>\n","protected":false},"author":1,"featured_media":0,"comment_status":"open","ping_status":"open","sticky":false,"template":"","format":"audio","meta":[],"categories":[18,19],"tags":[416,415,420,419,417,418],"_links":{"self":[{"href":"https:\/\/bestpropertymarket.cththemes.com\/wp-json\/wp\/v2\/posts\/440"}],"collection":[{"href":"https:\/\/bestpropertymarket.cththemes.com\/wp-json\/wp\/v2\/posts"}],"about":[{"href":"https:\/\/bestpropertymarket.cththemes.com\/wp-json\/wp\/v2\/types\/post"}],"author":[{"embeddable":true,"href":"https:\/\/bestpropertymarket.cththemes.com\/wp-json\/wp\/v2\/users\/1"}],"replies":[{"embeddable":true,"href":"https:\/\/bestpropertymarket.cththemes.com\/wp-json\/wp\/v2\/comments?post=440"}],"version-history":[{"count":2,"href":"https:\/\/bestpropertymarket.cththemes.com\/wp-json\/wp\/v2\/posts\/440\/revisions"}],"predecessor-version":[{"id":6483,"href":"https:\/\/bestpropertymarket.cththemes.com\/wp-json\/wp\/v2\/posts\/440\/revisions\/6483"}],"wp:attachment":[{"href":"https:\/\/bestpropertymarket.cththemes.com\/wp-json\/wp\/v2\/media?parent=440"}],"wp:term":[{"taxonomy":"category","embeddable":true,"href":"https:\/\/bestpropertymarket.cththemes.com\/wp-json\/wp\/v2\/categories?post=440"},{"taxonomy":"post_tag","embeddable":true,"href":"https:\/\/bestpropertymarket.cththemes.com\/wp-json\/wp\/v2\/tags?post=440"}],"curies":[{"name":"wp","href":"https:\/\/api.w.org\/{rel}","templated":true}]}}